[
    {
        "id": "1",
        "id_number": 1,
        "value": "戻る",
        "translation": "Return"
    },
    {
        "id": "2",
        "id_number": 2,
        "value": "装備変更",
        "translation": "Equipment change"
    },
    {
        "id": "3",
        "id_number": 3,
        "value": "バッグ",
        "translation": "Bag"
    },
    {
        "id": "4",
        "id_number": 4,
        "value": "クエスト",
        "translation": "Quest"
    },
    {
        "id": "5",
        "id_number": 5,
        "value": "ジェスチャー",
        "translation": "Gesture"
    },
    {
        "id": "6",
        "id_number": 6,
        "value": "マッチング",
        "translation": "Matching"
    },
    {
        "id": "7",
        "id_number": 7,
        "value": "マップ",
        "translation": "Map"
    },
    {
        "id": "8",
        "id_number": 8,
        "value": "ゲームを終了する",
        "translation": "Exit Game"
    },
    {
        "id": "9",
        "id_number": 9,
        "value": "パーティ",
        "translation": "Party"
    },
    {
        "id": "10",
        "id_number": 10,
        "value": "コミュニケート",
        "translation": "Communicate"
    },
    {
        "id": "11",
        "id_number": 11,
        "value": "オプション",
        "translation": "Options"
    },
    {
        "id": "12",
        "id_number": 12,
        "value": "キャラクター",
        "translation": "Character"
    },
    {
        "id": "13",
        "id_number": 13,
        "value": "キャラ選択へ戻る",
        "translation": "Character Selection"
    },
    {
        "id": "20",
        "id_number": 20,
        "value": "Command\nMenu",
        "translation": "Command\nMenu"
    },
    {
        "id": "21",
        "id_number": 21,
        "value": "Character",
        "translation": "Character"
    },
    {
        "id": "23",
        "id_number": 23,
        "value": "Bag",
        "translation": "Bag"
    },
    {
        "id": "24",
        "id_number": 24,
        "value": "Quest",
        "translation": "Quest"
    },
    {
        "id": "25",
        "id_number": 25,
        "value": "Gesture",
        "translation": "Gesture"
    },
    {
        "id": "26",
        "id_number": 26,
        "value": "Map",
        "translation": "Map"
    },
    {
        "id": "27",
        "id_number": 27,
        "value": "Communicate",
        "translation": "Communicate"
    },
    {
        "id": "28",
        "id_number": 28,
        "value": "Option",
        "translation": "Option"
    },
    {
        "id": "30",
        "id_number": 30,
        "value": "フォローリスト",
        "translation": "Follow list"
    },
    {
        "id": "31",
        "id_number": 31,
        "value": "フォロワーリスト",
        "translation": "Follower list"
    },
    {
        "id": "32",
        "id_number": 32,
        "value": "ブラックリスト",
        "translation": "blacklist"
    },
    {
        "id": "33",
        "id_number": 33,
        "value": "キャラクターサーチ",
        "translation": "Character search"
    },
    {
        "id": "34",
        "id_number": 34,
        "value": "プロフィール設定",
        "translation": "Profile settings"
    },
    {
        "id": "40",
        "id_number": 40,
        "value": "ステータス",
        "translation": "Status"
    },
    {
        "id": "41",
        "id_number": 41,
        "value": "衣装変更",
        "translation": "Costume change"
    },
    {
        "id": "42",
        "id_number": 42,
        "value": "冒険者アビリティ",
        "translation": "Adventurer ability"
    },
    {
        "id": "43",
        "id_number": 43,
        "value": "reserve",
        "translation": "reserve"
    },
    {
        "id": "44",
        "id_number": 44,
        "value": "アチーブメント",
        "translation": "Achievement"
    },
    {
        "id": "45",
        "id_number": 45,
        "value": "闘技場戦績",
        "translation": "Arena battle record"
    },
    {
        "id": "46",
        "id_number": 46,
        "value": "オートスタンプ",
        "translation": "Auto stamp"
    },
    {
        "id": "49",
        "id_number": 49,
        "value": "図鑑",
        "translation": "Picture book"
    },
    {
        "id": "50",
        "id_number": 50,
        "value": "Library",
        "translation": "Library"
    },
    {
        "id": "51",
        "id_number": 51,
        "value": "モンスター",
        "translation": "Monster"
    },
    {
        "id": "52",
        "id_number": 52,
        "value": "アイテム",
        "translation": "Item"
    },
    {
        "id": "53",
        "id_number": 53,
        "value": "レシピ集",
        "translation": "Recipe collection"
    },
    {
        "id": "54",
        "id_number": 54,
        "value": "地域",
        "translation": "Area"
    },
    {
        "id": "55",
        "id_number": 55,
        "value": "イマジン",
        "translation": "Imagine"
    },
    {
        "id": "56",
        "id_number": 56,
        "value": "旅の手引き",
        "translation": "Travel guide"
    },
    {
        "id": "57",
        "id_number": 57,
        "value": "レターボックス",
        "translation": "Letterbox"
    },
    {
        "id": "58",
        "id_number": 58,
        "value": "reserve",
        "translation": "reserve"
    },
    {
        "id": "59",
        "id_number": 59,
        "value": "reserve",
        "translation": "reserve"
    },
    {
        "id": "60",
        "id_number": 60,
        "value": "魂ランク",
        "translation": "Soul rank"
    },
    {
        "id": "61",
        "id_number": 61,
        "value": "ランキング一覧",
        "translation": "Ranking list"
    },
    {
        "id": "62",
        "id_number": 62,
        "value": "個人結果",
        "translation": "Personal results"
    }
]