[
    {
        "id": "0",
        "id_number": 0,
        "value": "コイン亭の親父さんが奢ってやるって言ってたゼ？\r\n今すぐ行くべきだ。というか行け。ククク……",
        "translation": ""
    },
    {
        "id": "0_ADD010",
        "id_number": 0,
        "value": "よう、お疲れ！\r\n順調に仕事をこなしてるみたいだな。So good！",
        "translation": ""
    },
    {
        "id": "0_ADD020",
        "id_number": 0,
        "value": "竜族やアバリティアには遭遇したか？\r\nあれから、いろいろと話を聞いてみたんだが……",
        "translation": ""
    },
    {
        "id": "0_ADD030",
        "id_number": 0,
        "value": "やはり、竜族のほうに何か動きがあるな。\r\n今までとは連中の行動パターンが異なっている",
        "translation": ""
    },
    {
        "id": "0_ADD040",
        "id_number": 0,
        "value": "思い返せば、バーンハルト公国襲撃事件も妙だった。\r\n竜族の連中、ある程度で『撤退』したらしいからな",
        "translation": ""
    },
    {
        "id": "0_ADD050",
        "id_number": 0,
        "value": "一度戦いになれば、やるかやられるか。\r\nだからこそ竜族は危険な奴らだったんだが……",
        "translation": ""
    },
    {
        "id": "0_ADD060",
        "id_number": 0,
        "value": "アバリティアといい、どうも厄介な匂いがする。\r\nヤバいと思ったら、いつでも声をかけろよ",
        "translation": ""
    },
    {
        "id": "3",
        "id_number": 3,
        "value": "何かあったんですか？\r\nジェイクが珍しく難しい顔をしているけど……",
        "translation": ""
    },
    {
        "id": "4",
        "id_number": 4,
        "value": "先生は、巨塔の遺跡について調べたいって言ってたわ",
        "translation": ""
    },
    {
        "id": "5",
        "id_number": 5,
        "value": "思い立ったら即行動の人だから、\r\n詳しいことは聞いてないのよ",
        "translation": ""
    }
]