[
    {
        "id": "1",
        "id_number": 1,
        "value": "FPS表示",
        "translation": ""
    },
    {
        "id": "2",
        "id_number": 2,
        "value": "キーガイド",
        "translation": ""
    },
    {
        "id": "3",
        "id_number": 3,
        "value": "クエスト",
        "translation": ""
    },
    {
        "id": "4",
        "id_number": 4,
        "value": "ミニマップ",
        "translation": ""
    },
    {
        "id": "5",
        "id_number": 5,
        "value": "パーティメンバー",
        "translation": ""
    },
    {
        "id": "6",
        "id_number": 6,
        "value": "パレット",
        "translation": ""
    },
    {
        "id": "7",
        "id_number": 7,
        "value": "スキル",
        "translation": ""
    },
    {
        "id": "8",
        "id_number": 8,
        "value": "アルティメットスキル",
        "translation": ""
    },
    {
        "id": "9",
        "id_number": 9,
        "value": "ステータス",
        "translation": ""
    },
    {
        "id": "10",
        "id_number": 10,
        "value": "トーク入力ウィンドウ",
        "translation": ""
    },
    {
        "id": "11",
        "id_number": 11,
        "value": "トークログ1",
        "translation": ""
    },
    {
        "id": "12",
        "id_number": 12,
        "value": "トークログ2",
        "translation": ""
    },
    {
        "id": "13",
        "id_number": 13,
        "value": "トークログ3",
        "translation": ""
    },
    {
        "id": "14",
        "id_number": 14,
        "value": "イマジンスキル",
        "translation": ""
    },
    {
        "id": "15",
        "id_number": 15,
        "value": "プライベートトークログ1",
        "translation": ""
    },
    {
        "id": "16",
        "id_number": 16,
        "value": "プライベートトークログ2",
        "translation": ""
    },
    {
        "id": "17",
        "id_number": 17,
        "value": "プライベートトークログ3",
        "translation": ""
    },
    {
        "id": "18",
        "id_number": 18,
        "value": "プライベートトークログ4",
        "translation": ""
    },
    {
        "id": "19",
        "id_number": 19,
        "value": "フォーカスターゲット情報",
        "translation": ""
    },
    {
        "id": "20",
        "id_number": 20,
        "value": "新着トーク",
        "translation": ""
    },
    {
        "id": "21",
        "id_number": 21,
        "value": "状態変化アイコン",
        "translation": ""
    },
    {
        "id": "22",
        "id_number": 22,
        "value": "未読レター",
        "translation": ""
    },
    {
        "id": "23",
        "id_number": 23,
        "value": "スキル",
        "translation": ""
    },
    {
        "id": "24",
        "id_number": 24,
        "value": "注意アラート",
        "translation": ""
    }
]