[
    {
        "id": "0",
        "id_number": 0,
        "value": "検索",
        "translation": ""
    },
    {
        "id": "1",
        "id_number": 1,
        "value": "カテゴリー",
        "translation": ""
    },
    {
        "id": "2",
        "id_number": 2,
        "value": "全体",
        "translation": ""
    },
    {
        "id": "3",
        "id_number": 3,
        "value": "左のリストを選択してください",
        "translation": ""
    },
    {
        "id": "11",
        "id_number": 11,
        "value": "モンスター",
        "translation": ""
    },
    {
        "id": "12",
        "id_number": 12,
        "value": "アイテム",
        "translation": ""
    },
    {
        "id": "13",
        "id_number": 13,
        "value": "武器",
        "translation": ""
    },
    {
        "id": "14",
        "id_number": 14,
        "value": "レシピ集",
        "translation": ""
    },
    {
        "id": "15",
        "id_number": 15,
        "value": "地域",
        "translation": ""
    },
    {
        "id": "16",
        "id_number": 16,
        "value": "イマジン",
        "translation": ""
    },
    {
        "id": "17",
        "id_number": 17,
        "value": "旅の手引き",
        "translation": ""
    },
    {
        "id": "21",
        "id_number": 21,
        "value": "Monster",
        "translation": ""
    },
    {
        "id": "22",
        "id_number": 22,
        "value": "Item",
        "translation": ""
    },
    {
        "id": "23",
        "id_number": 23,
        "value": "Weapon",
        "translation": ""
    },
    {
        "id": "24",
        "id_number": 24,
        "value": "Recipe",
        "translation": ""
    },
    {
        "id": "25",
        "id_number": 25,
        "value": "Country",
        "translation": ""
    },
    {
        "id": "26",
        "id_number": 26,
        "value": "Imagine",
        "translation": ""
    },
    {
        "id": "27",
        "id_number": 27,
        "value": "Bookmark",
        "translation": ""
    }
]